read_rapidpe/__init__.py
read_rapidpe/grid_point.py
read_rapidpe/io.py
read_rapidpe/p_astro.py
read_rapidpe/parser.py
read_rapidpe/plot.py
read_rapidpe/plugins/__init__.py
read_rapidpe/plugins/em_bright.py
read_rapidpe/result.py
read_rapidpe/transform.py
read_rapidpe-0.6.3.dist-info/METADATA
read_rapidpe-0.6.3.dist-info/WHEEL
read_rapidpe-0.6.3.dist-info/RECORD
