Metadata-Version: 2.1
Name: read-rapidpe
Version: 0.6.3
Summary: Read and analyse results generated by rapidpe-rift-pipe
Home-page: https://github.com/c0rychu/read-rapidpe
Author: Cory Chu
Author-email: cory@gwlab.page
Requires-Python: >=3.8,<4.0
Classifier: Programming Language :: Python :: 3
Classifier: Programming Language :: Python :: 3.8
Classifier: Programming Language :: Python :: 3.9
Classifier: Programming Language :: Python :: 3.10
Classifier: Programming Language :: Python :: 3.11
Requires-Dist: h5py (>=3.8.0,<4.0.0)
Requires-Dist: joblib (>=1.2.0,<2.0.0)
Requires-Dist: lalsuite (>=7.11,<8.0)
Requires-Dist: matplotlib (>=3.5.3,<4.0.0)
Requires-Dist: numpy (>=1.23.4,<2.0.0)
Requires-Dist: pandas (>=2.0.1,<3.0.0)
Requires-Dist: python-ligo-lw (>=1.8.3,<2.0.0)
Requires-Dist: scipy (>=1.8.1,<2.0.0)
Project-URL: Repository, https://git.ligo.org/yu-kuang.chu/read-rapidpe
